troveharvester/__init__.py
troveharvester/__main__.py
troveharvester-0.5.2.dist-info/COPYING.txt
troveharvester-0.5.2.dist-info/METADATA
troveharvester-0.5.2.dist-info/WHEEL
troveharvester-0.5.2.dist-info/entry_points.txt
troveharvester-0.5.2.dist-info/top_level.txt
troveharvester-0.5.2.dist-info/RECORD
