Metadata-Version: 2.1
Name: troveharvester
Version: 0.5.2
Summary: This tool is now archived, see trove-newspaper-harvester instead.
Home-page: https://github.com/wragge/troveharvester
Author: Tim Sherratt
Author-email: tim@discontents.com.au
License: CC0
License-File: COPYING.txt
Requires-Dist: pandas
Requires-Dist: requests
Requires-Dist: arrow
Requires-Dist: tqdm
Requires-Dist: pillow
Requires-Dist: bs4
Requires-Dist: lxml
Requires-Dist: html2text
Requires-Dist: trove-query-parser
Requires-Dist: trove-newspaper-images
